macromol_census/__init__.py
macromol_census/database_io.py
macromol_census/error.py
macromol_census/extract_fasta.py
macromol_census/extract_nonredundant_assemblies.py
macromol_census/find_identical_branched_entities.py
macromol_census/find_identical_ligands.py
macromol_census/ingest_blacklist.py
macromol_census/ingest_chemicals.py
macromol_census/ingest_entity_clusters.py
macromol_census/ingest_nonspecific_ligands.py
macromol_census/ingest_structures.py
macromol_census/ingest_validation.py
macromol_census/init.py
macromol_census/pick_assemblies.py
macromol_census/rank_assemblies.py
macromol_census/rank_structures.py
macromol_census/util.py
macromol_census-0.3.0.dist-info/entry_points.txt
macromol_census-0.3.0.dist-info/WHEEL
macromol_census-0.3.0.dist-info/METADATA
macromol_census-0.3.0.dist-info/RECORD
