Metadata-Version: 2.3
Name: macromol_census
Version: 0.3.0
Summary: Tools for creating machine-learning datasets from macromolecular structure 
Author-email: Kale Kundert <kale@thekunderts.net>
Requires-Python: ~=3.10
Classifier: Programming Language :: Python :: 3
Requires-Dist: biopython
Requires-Dist: docopt
Requires-Dist: duckdb>=0.10.0
Requires-Dist: gemmi
Requires-Dist: more_itertools
Requires-Dist: networkx
Requires-Dist: numpy
Requires-Dist: polars
Requires-Dist: pyarrow
Requires-Dist: scipy
Requires-Dist: tidyexc
Requires-Dist: tqdm
Requires-Dist: sphinx ; extra == "doc"
Requires-Dist: sphinx_rtd_theme ; extra == "doc"
Requires-Dist: autoclasstoc ; extra == "doc"
Requires-Dist: pytest ; extra == "test"
Requires-Dist: parametrize_from_file ; extra == "test"
Requires-Dist: pytest_unordered ; extra == "test"
Project-URL: Bug Tracker, https://github.com/kalekundert/macromol_census/issues
Project-URL: Continuous Integration, https://github.com/kalekundert/macromol_census/actions
Project-URL: Documentation, https://macromol-census.readthedocs.io/en/latest/
Project-URL: Test Coverage, https://coveralls.io/github/kalekundert/macromol_census
Project-URL: Version Control, https://github.com/kalekundert/macromol_census
Provides-Extra: doc
Provides-Extra: test
